win_toaster/__init__.py
win_toaster/data/__init__.py
win_toaster/data/python.ico
WinToaster-0.1.0.dist-info/LICENSE
WinToaster-0.1.0.dist-info/METADATA
WinToaster-0.1.0.dist-info/WHEEL
WinToaster-0.1.0.dist-info/top_level.txt
WinToaster-0.1.0.dist-info/RECORD
