Metadata-Version: 2.1
Name: WinToaster
Version: 0.1.0
Summary: Effortlessly create toast notifications for windows 10.
Home-page: https://github.com/MaliciousFiles/WinToaster/
Author: Malcolm Roalson
Author-email: mtroalson@gmail.com
License: MIT
Platform: UNKNOWN
Classifier: License :: OSI Approved :: MIT License
Classifier: Programming Language :: Python
Classifier: Programming Language :: Python :: 3
Classifier: Programming Language :: Python :: 3.6
Classifier: Programming Language :: Python :: Implementation :: CPython
Requires-Python: >=3.6.0
Requires-Dist: pywin32
Requires-Dist: setuptools
Requires-Dist: importlib-resources ; python_version < "3.7"
